fl0/__init__.py
fl0/bin/.gitkeep
fl0/proto/common/v1/common.proto
fl0/proto/common/v1/common_pb2.py
fl0/proto/common/v1/common_pb2.pyi
fl0/proto/core/collector/v1/collector_service.proto
fl0/proto/core/collector/v1/collector_service_pb2.py
fl0/proto/core/collector/v1/collector_service_pb2.pyi
fl0/proto/core/collector/v1/collector_service_pb2_grpc.py
fl0/proto/core/health/v1/health_service.proto
fl0/proto/core/lifecycle/__init__.py
fl0/proto/core/lifecycle/v1/__init__.py
fl0/proto/core/lifecycle/v1/lifecycle_service.proto
fl0/proto/core/lifecycle/v1/lifecycle_service_pb2.py
fl0/proto/core/lifecycle/v1/lifecycle_service_pb2.pyi
fl0/proto/core/lifecycle/v1/lifecycle_service_pb2_grpc.py
fl0/proto/record/v1/record.proto
fl0/proto/record/v1/record_pb2.py
fl0/proto/record/v1/record_pb2.pyi
fl0/bin/core
fl0swan-0.1.3.dist-info/METADATA
fl0swan-0.1.3.dist-info/WHEEL
fl0swan-0.1.3.dist-info/RECORD
