Metadata-Version: 2.4
Name: fl0swan
Version: 0.1.3
Summary: Add your description here
Author-email: Fl0rencess720 <your.email@example.com>
Requires-Python: >=3.12
Requires-Dist: grpcio-tools>=1.76.0
Requires-Dist: grpcio>=1.76.0
